yecoai_cognitive_layer/__init__.py
yecoai_cognitive_layer/feature_engine.py
yecoai_cognitive_layer/model.py
yecoai_cognitive_layer/weights.json
yecoai_cognitive_layer-0.1.0.dist-info/licenses/LICENSE
yecoai_cognitive_layer-0.1.0.dist-info/licenses/NOTICE
yecoai_cognitive_layer-0.1.0.dist-info/METADATA
yecoai_cognitive_layer-0.1.0.dist-info/WHEEL
yecoai_cognitive_layer-0.1.0.dist-info/top_level.txt
yecoai_cognitive_layer-0.1.0.dist-info/RECORD
