Metadata-Version: 2.4
Name: yecoai-cognitive-layer
Version: 0.1.0
Summary: Lightweight cognitive protection layer for LLM systems
Author-email: YecoAI <contact@yecoai.dev>
License:                                  Apache License
Project-URL: Homepage, https://github.com/YecoAI/yecoai-mini-llm-layer
Project-URL: Source, https://github.com/YecoAI/yecoai-mini-llm-layer
Keywords: ai,llm,guard,cognitive,loop-detection
Classifier: Programming Language :: Python :: 3
Classifier: License :: OSI Approved :: Apache Software License
Classifier: Operating System :: OS Independent
Requires-Python: >=3.9
License-File: LICENSE
License-File: NOTICE
Dynamic: license-file
